pytorch_minimize-0.1.0.dist-info/licenses/LICENSE
torchmin/__init__.py
torchmin/_optimize.py
torchmin/_version.py
torchmin/benchmarks.py
torchmin/bfgs.py
torchmin/cg.py
torchmin/function.py
torchmin/line_search.py
torchmin/minimize.py
torchmin/minimize_constr.py
torchmin/newton.py
torchmin/constrained/frankwolfe.py
torchmin/constrained/lbfgsb.py
torchmin/constrained/trust_constr.py
torchmin/lstsq/__init__.py
torchmin/lstsq/cg.py
torchmin/lstsq/common.py
torchmin/lstsq/least_squares.py
torchmin/lstsq/linear_operator.py
torchmin/lstsq/lsmr.py
torchmin/lstsq/trf.py
torchmin/optim/__init__.py
torchmin/optim/minimizer.py
torchmin/optim/scipy_minimizer.py
torchmin/trustregion/__init__.py
torchmin/trustregion/base.py
torchmin/trustregion/dogleg.py
torchmin/trustregion/exact.py
torchmin/trustregion/krylov.py
torchmin/trustregion/ncg.py
pytorch_minimize-0.1.0.dist-info/METADATA
pytorch_minimize-0.1.0.dist-info/WHEEL
pytorch_minimize-0.1.0.dist-info/top_level.txt
pytorch_minimize-0.1.0.dist-info/RECORD
