Metadata-Version: 2.4
Name: pytorch-minimize
Version: 0.1.0
Summary: Newton and Quasi-Newton optimization with PyTorch
Author-email: Reuben Feinman <reuben.feinman@nyu.edu>
License: MIT License
Project-URL: Documentation, https://pytorch-minimize.readthedocs.io
Project-URL: Homepage, https://github.com/rfeinman/pytorch-minimize
Classifier: Programming Language :: Python :: 3
Classifier: License :: OSI Approved :: MIT License
Classifier: Operating System :: OS Independent
Requires-Python: >=3.7
License-File: LICENSE
Requires-Dist: numpy>=1.18.0
Requires-Dist: scipy>=1.6
Requires-Dist: torch>=1.9.0
Provides-Extra: dev
Requires-Dist: pytest; extra == "dev"
Provides-Extra: docs
Requires-Dist: sphinx==3.5.3; extra == "docs"
Requires-Dist: jinja2<3.1; extra == "docs"
Requires-Dist: sphinx_rtd_theme==0.5.2; extra == "docs"
Requires-Dist: readthedocs-sphinx-search==0.3.2; extra == "docs"
Dynamic: license-file
